LICENSE
MANIFEST.in
README.md
ez_setup.py
nebfa.py
setup.py
nebfa.egg-info/PKG-INFO
nebfa.egg-info/SOURCES.txt
nebfa.egg-info/dependency_links.txt
nebfa.egg-info/not-zip-safe
nebfa.egg-info/top_level.txt
test/t.py
test/test-basic.py
test/test-multi-def.py
test/test-multi.py
test/data/basic.fa
test/data/multi.fa
test/data/multidef.fa