Metadata-Version: 1.0
Name: nebfa
Version: 0.0.2
Summary: Fasta file parser.
Home-page: http://github.com/davisp/nebgb
Author: Paul Joseph Davis
Author-email: davisp@neb.com
License: MIT
Keywords: bioinformatics fasta parser
Platform: any
Classifier: Development Status :: 3 - Alpha
Classifier: Intended Audience :: Developers
Classifier: Intended Audience :: Science/Research
Classifier: License :: OSI Approved :: MIT License
Classifier: Natural Language :: English
Classifier: Operating System :: OS Independent
Classifier: Programming Language :: Python
Classifier: Topic :: Scientific/Engineering :: Bio-Informatics
Classifier: Topic :: Software Development :: Libraries :: Python Modules
